README.txt
setup.cfg
setup.py
Products/__init__.py
Products.QuickImporter.egg-info/PKG-INFO
Products.QuickImporter.egg-info/SOURCES.txt
Products.QuickImporter.egg-info/dependency_links.txt
Products.QuickImporter.egg-info/entry_points.txt
Products.QuickImporter.egg-info/namespace_packages.txt
Products.QuickImporter.egg-info/not-zip-safe
Products.QuickImporter.egg-info/requires.txt
Products.QuickImporter.egg-info/top_level.txt
Products/QuickImporter/QuickImporter.py
Products/QuickImporter/__init__.py
Products/QuickImporter/configure.zcml
Products/QuickImporter/refresh.txt
Products/QuickImporter/tests.py
Products/QuickImporter/version.txt
Products/QuickImporter/dtml/quickImporterForm.dtml
docs/HISTORY.txt
docs/INSTALL.txt
docs/LICENSE.GPL
docs/LICENSE.txt