Metadata-Version: 1.0
Name: Products.QuickImporter
Version: 0.2.1
Summary: You can 'upload .zexp files from your local machine
Home-page: http://www.zope.org/Members/mojix/QuickImporter/
Author: Michiharu Sakurai
Author-email: mojix at mojix.org
License: GPL
Platform: UNKNOWN
Classifier: Framework :: Plone
Classifier: Programming Language :: Python
Classifier: Topic :: Software Development :: Libraries :: Python Modules
